win_onnx/__init__.py
win_onnx/winml.cp310-win_amd64.pyd
win_onnx/winml.cp38-win_amd64.pyd
win_onnx/winml.cp39-win_amd64.pyd
win_onnx/winml.pyi
win_onnx-0.1.1.dist-info/LICENSE
win_onnx-0.1.1.dist-info/METADATA
win_onnx-0.1.1.dist-info/WHEEL
win_onnx-0.1.1.dist-info/top_level.txt
win_onnx-0.1.1.dist-info/RECORD
